{"nodes": [{"id": "d_projects_personal_hostello_src_app_api_reviews_id_route_ts", "label": "route.ts", "file_type": "code", "source_file": "D:\\Projects\\Personal\\hostello\\src\\app\\api\\reviews\\[id]\\route.ts", "source_location": "L1"}, {"id": "id_route_put", "label": "PUT()", "file_type": "code", "source_file": "D:\\Projects\\Personal\\hostello\\src\\app\\api\\reviews\\[id]\\route.ts", "source_location": "L16"}, {"id": "id_route_delete", "label": "DELETE()", "file_type": "code", "source_file": "D:\\Projects\\Personal\\hostello\\src\\app\\api\\reviews\\[id]\\route.ts", "source_location": "L116"}], "edges": [{"source": "d_projects_personal_hostello_src_app_api_reviews_id_route_ts", "target": "server", "relation": "imports_from", "context": "import", "confidence": "EXTRACTED", "source_file": "D:\\Projects\\Personal\\hostello\\src\\app\\api\\reviews\\[id]\\route.ts", "source_location": "L1", "weight": 1.0}, {"source": "d_projects_personal_hostello_src_app_api_reviews_id_route_ts", "target": "d_projects_personal_hostello_src_lib_auth_config", "relation": "imports_from", "context": "import", "confidence": "EXTRACTED", "source_file": "D:\\Projects\\Personal\\hostello\\src\\app\\api\\reviews\\[id]\\route.ts", "source_location": "L2", "weight": 1.0}, {"source": "d_projects_personal_hostello_src_app_api_reviews_id_route_ts", "target": "auth_config_auth", "relation": "imports", "context": "import", "confidence": "EXTRACTED", "source_file": "D:\\Projects\\Personal\\hostello\\src\\app\\api\\reviews\\[id]\\route.ts", "source_location": "L2", "weight": 1.0}, {"source": "d_projects_personal_hostello_src_app_api_reviews_id_route_ts", "target": "d_projects_personal_hostello_src_lib_db", "relation": "imports_from", "context": "import", "confidence": "EXTRACTED", "source_file": "D:\\Projects\\Personal\\hostello\\src\\app\\api\\reviews\\[id]\\route.ts", "source_location": "L3", "weight": 1.0}, {"source": "d_projects_personal_hostello_src_app_api_reviews_id_route_ts", "target": "lib_db_db", "relation": "imports", "context": "import", "confidence": "EXTRACTED", "source_file": "D:\\Projects\\Personal\\hostello\\src\\app\\api\\reviews\\[id]\\route.ts", "source_location": "L3", "weight": 1.0}, {"source": "d_projects_personal_hostello_src_app_api_reviews_id_route_ts", "target": "d_projects_personal_hostello_src_lib_validations", "relation": "imports_from", "context": "import", "confidence": "EXTRACTED", "source_file": "D:\\Projects\\Personal\\hostello\\src\\app\\api\\reviews\\[id]\\route.ts", "source_location": "L4", "weight": 1.0}, {"source": "d_projects_personal_hostello_src_app_api_reviews_id_route_ts", "target": "lib_validations_reviewschema", "relation": "imports", "context": "import", "confidence": "EXTRACTED", "source_file": "D:\\Projects\\Personal\\hostello\\src\\app\\api\\reviews\\[id]\\route.ts", "source_location": "L4", "weight": 1.0}, {"source": "d_projects_personal_hostello_src_app_api_reviews_id_route_ts", "target": "d_projects_personal_hostello_src_lib_typesense_sync", "relation": "imports_from", "context": "import", "confidence": "EXTRACTED", "source_file": "D:\\Projects\\Personal\\hostello\\src\\app\\api\\reviews\\[id]\\route.ts", "source_location": "L5", "weight": 1.0}, {"source": "d_projects_personal_hostello_src_app_api_reviews_id_route_ts", "target": "lib_typesense_sync_indexsinglehostel", "relation": "imports", "context": "import", "confidence": "EXTRACTED", "source_file": "D:\\Projects\\Personal\\hostello\\src\\app\\api\\reviews\\[id]\\route.ts", "source_location": "L5", "weight": 1.0}, {"source": "d_projects_personal_hostello_src_app_api_reviews_id_route_ts", "target": "id_route_put", "relation": "contains", "confidence": "EXTRACTED", "source_file": "D:\\Projects\\Personal\\hostello\\src\\app\\api\\reviews\\[id]\\route.ts", "source_location": "L16", "weight": 1.0}, {"source": "d_projects_personal_hostello_src_app_api_reviews_id_route_ts", "target": "id_route_delete", "relation": "contains", "confidence": "EXTRACTED", "source_file": "D:\\Projects\\Personal\\hostello\\src\\app\\api\\reviews\\[id]\\route.ts", "source_location": "L116", "weight": 1.0}], "raw_calls": [{"caller_nid": "id_route_put", "callee": "auth", "is_member_call": false, "source_file": "D:\\Projects\\Personal\\hostello\\src\\app\\api\\reviews\\[id]\\route.ts", "source_location": "L21"}, {"caller_nid": "id_route_put", "callee": "json", "is_member_call": true, "source_file": "D:\\Projects\\Personal\\hostello\\src\\app\\api\\reviews\\[id]\\route.ts", "source_location": "L23"}, {"caller_nid": "id_route_put", "callee": "findUnique", "is_member_call": true, "source_file": "D:\\Projects\\Personal\\hostello\\src\\app\\api\\reviews\\[id]\\route.ts", "source_location": "L29"}, {"caller_nid": "id_route_put", "callee": "json", "is_member_call": true, "source_file": "D:\\Projects\\Personal\\hostello\\src\\app\\api\\reviews\\[id]\\route.ts", "source_location": "L39"}, {"caller_nid": "id_route_put", "callee": "json", "is_member_call": true, "source_file": "D:\\Projects\\Personal\\hostello\\src\\app\\api\\reviews\\[id]\\route.ts", "source_location": "L47"}, {"caller_nid": "id_route_put", "callee": "json", "is_member_call": true, "source_file": "D:\\Projects\\Personal\\hostello\\src\\app\\api\\reviews\\[id]\\route.ts", "source_location": "L54"}, {"caller_nid": "id_route_put", "callee": "safeParse", "is_member_call": true, "source_file": "D:\\Projects\\Personal\\hostello\\src\\app\\api\\reviews\\[id]\\route.ts", "source_location": "L55"}, {"caller_nid": "id_route_put", "callee": "json", "is_member_call": true, "source_file": "D:\\Projects\\Personal\\hostello\\src\\app\\api\\reviews\\[id]\\route.ts", "source_location": "L58"}, {"caller_nid": "id_route_put", "callee": "flatten", "is_member_call": true, "source_file": "D:\\Projects\\Personal\\hostello\\src\\app\\api\\reviews\\[id]\\route.ts", "source_location": "L59"}, {"caller_nid": "id_route_put", "callee": "$transaction", "is_member_call": true, "source_file": "D:\\Projects\\Personal\\hostello\\src\\app\\api\\reviews\\[id]\\route.ts", "source_location": "L65"}, {"caller_nid": "id_route_put", "callee": "catch", "is_member_call": true, "source_file": "D:\\Projects\\Personal\\hostello\\src\\app\\api\\reviews\\[id]\\route.ts", "source_location": "L97"}, {"caller_nid": "id_route_put", "callee": "indexSingleHostel", "is_member_call": false, "source_file": "D:\\Projects\\Personal\\hostello\\src\\app\\api\\reviews\\[id]\\route.ts", "source_location": "L97"}, {"caller_nid": "id_route_put", "callee": "json", "is_member_call": true, "source_file": "D:\\Projects\\Personal\\hostello\\src\\app\\api\\reviews\\[id]\\route.ts", "source_location": "L101"}, {"caller_nid": "id_route_put", "callee": "error", "is_member_call": true, "source_file": "D:\\Projects\\Personal\\hostello\\src\\app\\api\\reviews\\[id]\\route.ts", "source_location": "L103"}, {"caller_nid": "id_route_put", "callee": "json", "is_member_call": true, "source_file": "D:\\Projects\\Personal\\hostello\\src\\app\\api\\reviews\\[id]\\route.ts", "source_location": "L104"}, {"caller_nid": "id_route_delete", "callee": "auth", "is_member_call": false, "source_file": "D:\\Projects\\Personal\\hostello\\src\\app\\api\\reviews\\[id]\\route.ts", "source_location": "L121"}, {"caller_nid": "id_route_delete", "callee": "json", "is_member_call": true, "source_file": "D:\\Projects\\Personal\\hostello\\src\\app\\api\\reviews\\[id]\\route.ts", "source_location": "L123"}, {"caller_nid": "id_route_delete", "callee": "findUnique", "is_member_call": true, "source_file": "D:\\Projects\\Personal\\hostello\\src\\app\\api\\reviews\\[id]\\route.ts", "source_location": "L129"}, {"caller_nid": "id_route_delete", "callee": "json", "is_member_call": true, "source_file": "D:\\Projects\\Personal\\hostello\\src\\app\\api\\reviews\\[id]\\route.ts", "source_location": "L138"}, {"caller_nid": "id_route_delete", "callee": "json", "is_member_call": true, "source_file": "D:\\Projects\\Personal\\hostello\\src\\app\\api\\reviews\\[id]\\route.ts", "source_location": "L146"}, {"caller_nid": "id_route_delete", "callee": "$transaction", "is_member_call": true, "source_file": "D:\\Projects\\Personal\\hostello\\src\\app\\api\\reviews\\[id]\\route.ts", "source_location": "L153"}, {"caller_nid": "id_route_delete", "callee": "catch", "is_member_call": true, "source_file": "D:\\Projects\\Personal\\hostello\\src\\app\\api\\reviews\\[id]\\route.ts", "source_location": "L174"}, {"caller_nid": "id_route_delete", "callee": "indexSingleHostel", "is_member_call": false, "source_file": "D:\\Projects\\Personal\\hostello\\src\\app\\api\\reviews\\[id]\\route.ts", "source_location": "L174"}, {"caller_nid": "id_route_delete", "callee": "json", "is_member_call": true, "source_file": "D:\\Projects\\Personal\\hostello\\src\\app\\api\\reviews\\[id]\\route.ts", "source_location": "L178"}, {"caller_nid": "id_route_delete", "callee": "error", "is_member_call": true, "source_file": "D:\\Projects\\Personal\\hostello\\src\\app\\api\\reviews\\[id]\\route.ts", "source_location": "L180"}, {"caller_nid": "id_route_delete", "callee": "json", "is_member_call": true, "source_file": "D:\\Projects\\Personal\\hostello\\src\\app\\api\\reviews\\[id]\\route.ts", "source_location": "L181"}]}