{"nodes": [{"id": "d_projects_personal_hostello_src_lib_email_templates_price_alert_ts", "label": "price-alert.ts", "file_type": "code", "source_file": "D:\\Projects\\Personal\\hostello\\src\\lib\\email-templates\\price-alert.ts", "source_location": "L1"}, {"id": "email_templates_price_alert_formatprice", "label": "formatPrice()", "file_type": "code", "source_file": "D:\\Projects\\Personal\\hostello\\src\\lib\\email-templates\\price-alert.ts", "source_location": "L13"}, {"id": "email_templates_price_alert_pricealertemail", "label": "priceAlertEmail()", "file_type": "code", "source_file": "D:\\Projects\\Personal\\hostello\\src\\lib\\email-templates\\price-alert.ts", "source_location": "L21"}], "edges": [{"source": "d_projects_personal_hostello_src_lib_email_templates_price_alert_ts", "target": "d_projects_personal_hostello_src_lib_email", "relation": "imports_from", "context": "import", "confidence": "EXTRACTED", "source_file": "D:\\Projects\\Personal\\hostello\\src\\lib\\email-templates\\price-alert.ts", "source_location": "L1", "weight": 1.0}, {"source": "d_projects_personal_hostello_src_lib_email_templates_price_alert_ts", "target": "lib_email_escapehtml", "relation": "imports", "context": "import", "confidence": "EXTRACTED", "source_file": "D:\\Projects\\Personal\\hostello\\src\\lib\\email-templates\\price-alert.ts", "source_location": "L1", "weight": 1.0}, {"source": "d_projects_personal_hostello_src_lib_email_templates_price_alert_ts", "target": "d_projects_personal_hostello_src_lib_email_templates_layout", "relation": "imports_from", "context": "import", "confidence": "EXTRACTED", "source_file": "D:\\Projects\\Personal\\hostello\\src\\lib\\email-templates\\price-alert.ts", "source_location": "L2", "weight": 1.0}, {"source": "d_projects_personal_hostello_src_lib_email_templates_price_alert_ts", "target": "email_templates_layout_emaillayout", "relation": "imports", "context": "import", "confidence": "EXTRACTED", "source_file": "D:\\Projects\\Personal\\hostello\\src\\lib\\email-templates\\price-alert.ts", "source_location": "L2", "weight": 1.0}, {"source": "d_projects_personal_hostello_src_lib_email_templates_price_alert_ts", "target": "email_templates_layout_emailbutton", "relation": "imports", "context": "import", "confidence": "EXTRACTED", "source_file": "D:\\Projects\\Personal\\hostello\\src\\lib\\email-templates\\price-alert.ts", "source_location": "L2", "weight": 1.0}, {"source": "d_projects_personal_hostello_src_lib_email_templates_price_alert_ts", "target": "email_templates_price_alert_formatprice", "relation": "contains", "confidence": "EXTRACTED", "source_file": "D:\\Projects\\Personal\\hostello\\src\\lib\\email-templates\\price-alert.ts", "source_location": "L13", "weight": 1.0}, {"source": "d_projects_personal_hostello_src_lib_email_templates_price_alert_ts", "target": "email_templates_price_alert_pricealertemail", "relation": "contains", "confidence": "EXTRACTED", "source_file": "D:\\Projects\\Personal\\hostello\\src\\lib\\email-templates\\price-alert.ts", "source_location": "L21", "weight": 1.0}, {"source": "email_templates_price_alert_pricealertemail", "target": "email_templates_price_alert_formatprice", "relation": "calls", "context": "call", "confidence": "EXTRACTED", "source_file": "D:\\Projects\\Personal\\hostello\\src\\lib\\email-templates\\price-alert.ts", "source_location": "L45", "weight": 1.0}], "raw_calls": [{"caller_nid": "email_templates_price_alert_formatprice", "callee": "format", "is_member_call": true, "source_file": "D:\\Projects\\Personal\\hostello\\src\\lib\\email-templates\\price-alert.ts", "source_location": "L14"}, {"caller_nid": "email_templates_price_alert_pricealertemail", "callee": "escapeHtml", "is_member_call": false, "source_file": "D:\\Projects\\Personal\\hostello\\src\\lib\\email-templates\\price-alert.ts", "source_location": "L29"}, {"caller_nid": "email_templates_price_alert_pricealertemail", "callee": "escapeHtml", "is_member_call": false, "source_file": "D:\\Projects\\Personal\\hostello\\src\\lib\\email-templates\\price-alert.ts", "source_location": "L30"}, {"caller_nid": "email_templates_price_alert_pricealertemail", "callee": "emailButton", "is_member_call": false, "source_file": "D:\\Projects\\Personal\\hostello\\src\\lib\\email-templates\\price-alert.ts", "source_location": "L58"}, {"caller_nid": "email_templates_price_alert_pricealertemail", "callee": "emailLayout", "is_member_call": false, "source_file": "D:\\Projects\\Personal\\hostello\\src\\lib\\email-templates\\price-alert.ts", "source_location": "L68"}]}